django_recompi/__init__.py
django_recompi/apps.py
django_recompi/models.py
django_recompi-2.2.1.dist-info/LICENSE
django_recompi-2.2.1.dist-info/METADATA
django_recompi-2.2.1.dist-info/WHEEL
django_recompi-2.2.1.dist-info/top_level.txt
django_recompi-2.2.1.dist-info/RECORD
