Metadata-Version: 2.1
Name: django-recompi
Version: 2.2.1
Summary: Integration of RecomPI with Django models for recommendation and tracking functionalities.
Author-email: RecomPI <tech@recompi.com>
Project-URL: Source, https://github.com/recompi/django-recompi
Project-URL: RecomPI Package, https://pypi.org/project/recompi
Project-URL: Use Cases, https://www.recompi.com/category/use-cases/documents-use-cases
Project-URL: Bug Tracker, https://github.com/recompi/django-recompi/issues
Project-URL: Website, https://www.recompi.com
Project-URL: Panel, https://panel.recompi.com
Project-URL: Wordpress Plugin, https://www.zhaket.com/web/recompi-plugin
Keywords: django,recompi,recommendation,tracking,recommender system,machine learning,data science,web development
Classifier: Development Status :: 5 - Production/Stable
Classifier: Framework :: Django
Classifier: Framework :: Django :: 2.2
Classifier: Framework :: Django :: 3.0
Classifier: Framework :: Django :: 3.1
Classifier: Framework :: Django :: 3.2
Classifier: Framework :: Django :: 4.0
Classifier: Framework :: Django :: 5.0
Classifier: Environment :: Web Environment
Classifier: Intended Audience :: Developers
Classifier: License :: OSI Approved :: MIT License
Classifier: Operating System :: OS Independent
Classifier: Programming Language :: Python :: 3
Classifier: Programming Language :: Python :: 3 :: Only
Classifier: Topic :: Software Development :: Libraries :: Python Modules
Requires-Python: >=3
License-File: LICENSE
Requires-Dist: recompi <2.1,>=2.0.20
Requires-Dist: Django >=2
